{
    "$schema": "https://schema.management.azure.com/schemas/2019-04-01/deploymentTemplate.json#",
    "contentVersion": "1.0.0.0",
    "parameters": {
        "envGuid":{
            "type": "string",
            "defaultvalue": ""
        }
    },
    "functions": [],
    "variables": {},
    "resources": [

        {
            "name": "vnet-box",
            "type": "Microsoft.Network/virtualNetworks",
            "apiVersion": "2019-11-01",
            "location": "[resourceGroup().location]",
            "tags": {
                "displayName": "vnet-box",
                "envGuid": "[parameters('envGuid')]"
            },
            "properties": {
                "addressSpace": {
                    "addressPrefixes": [
                        "10.0.0.0/16"
                    ]
                },
                "subnets": [
                    {
                        "name": "Subnet-0",
                        "properties": {
                            "addressPrefix": "10.0.0.0/24"
                        }
                    },
                    {
                        "name": "Subnet-1",
                        "properties": {
                            "addressPrefix": "10.0.1.0/24"
                        }
                    },
                    {
                        "name": "Subnet-255-lb-fe",
                        "properties": {
                            "addressPrefix": "10.0.255.0/24"
                        }
                    }

                ]
            }
        }
    ],
    "outputs": {}
}